tinycardl/__init__.py
tinycardl/main.py
tinycardl-1.0.0.dist-info/entry_points.txt
tinycardl-1.0.0.dist-info/WHEEL
tinycardl-1.0.0.dist-info/METADATA
tinycardl-1.0.0.dist-info/RECORD
