Metadata-Version: 2.1
Name: tinycardl
Version: 1.0.0
Summary: Download your cards
Home-page: https://github.com/batisteo/tinycardl
License: MIT
Author: Baptiste Darthenay
Author-email: baptiste.darthenay@gmail.com
Requires-Python: >=3.8,<4.0
Classifier: License :: OSI Approved :: MIT License
Classifier: Programming Language :: Python :: 3
Classifier: Programming Language :: Python :: 3.8
Requires-Dist: aiocsv (>=1.1.0,<2.0.0)
Requires-Dist: aiofiles (>=0.5.0,<0.6.0)
Requires-Dist: aioify (>=0.3.2,<0.4.0)
Requires-Dist: httpx (>=0.14.1,<0.15.0)
Requires-Dist: httpx-auth (>=0.5.0,<0.6.0)
Requires-Dist: python-jose (>=3.2.0,<4.0.0)
Project-URL: Repository, https://github.com/batisteo/tinycardl
